ndx_sound/spec/ndx-sound.extensions.yaml
ndx_sound/spec/ndx-sound.namespace.yaml
ndx_sound/__init__.py
ndx_sound/widgets.py
ndx_sound/testing/__init__.py
ndx_sound/testing/mock.py
ndx_sound-0.2.2.dist-info/METADATA
ndx_sound-0.2.2.dist-info/WHEEL
ndx_sound-0.2.2.dist-info/licenses/LICENSE.txt
ndx_sound-0.2.2.dist-info/RECORD
