Metadata-Version: 2.4
Name: ndx-sound
Version: 0.2.2
Summary: Represent acoustic stimuli and responses
Project-URL: Homepage, https://github.com/catalystneuro/ndx-sound
Project-URL: Bug Tracker, https://github.com/catalystneuro/ndx-sound/issues
Author-email: Ben Dichter <ben.dichter@catalystneuro.com>
License: BSD-3
License-File: LICENSE.txt
Keywords: NWB,NeurodataWithoutBorders,ndx-extension,nwb-extension
Classifier: Development Status :: 3 - Alpha
Classifier: Intended Audience :: Developers
Classifier: Intended Audience :: Science/Research
Classifier: License :: OSI Approved :: BSD License
Classifier: Operating System :: OS Independent
Classifier: Programming Language :: Python :: 3.10
Classifier: Programming Language :: Python :: 3.11
Classifier: Programming Language :: Python :: 3.12
Classifier: Programming Language :: Python :: 3.13
Requires-Python: >=3.10
Requires-Dist: hdmf>=2.5.6
Requires-Dist: pynwb>=1.5.0
Provides-Extra: dev
Requires-Dist: hdmf-docutils==0.4.4; extra == 'dev'
Requires-Dist: pytest-subtests==0.6.0; extra == 'dev'
Requires-Dist: pytest>=6.2.5; extra == 'dev'
Provides-Extra: widgets
Requires-Dist: ipyvolume==0.6.0a10; (python_version >= '3.10') and extra == 'widgets'
Requires-Dist: nwbwidgets>=0.8.0; extra == 'widgets'
